MANIFEST.in
README.txt
RELEASE-VERSION
pavement.py
paver-minilib.zip
setup.py
version.py
hv_switching_board/__init__.py
hv_switching_board/__init__.pyc
hv_switching_board/driver.py
hv_switching_board/driver.pyc
hv_switching_board/Arduino/hv_switching_board/Config.h
hv_switching_board/Arduino/hv_switching_board/Config.h.skeleton
hv_switching_board/Arduino/hv_switching_board/HVSwitchingBoard.cpp
hv_switching_board/Arduino/hv_switching_board/HVSwitchingBoard.h
hv_switching_board/Arduino/hv_switching_board/HVSwitchingBoard.o
hv_switching_board/Arduino/hv_switching_board/SConscript
hv_switching_board/Arduino/hv_switching_board/hv_switching_board.ino
hv_switching_board/bin/__init__.py
hv_switching_board/bin/__init__.pyc
hv_switching_board/bin/upload.py
hv_switching_board/firmware/hv_switching_board.hex
wheeler.hv_switching_board.egg-info/PKG-INFO
wheeler.hv_switching_board.egg-info/SOURCES.txt
wheeler.hv_switching_board.egg-info/dependency_links.txt
wheeler.hv_switching_board.egg-info/requires.txt
wheeler.hv_switching_board.egg-info/top_level.txt