Metadata-Version: 1.0
Name: wheeler.hv-switching-board
Version: 0.4
Summary: Arduino-based high-voltage switching board firmware and Python API.
Home-page: https://github.com/wheeler-microfluidics/hv-switching-board-firmware
Author: Ryan Fobel
Author-email: ryan@fobel.net
License: GPLv2
Platform: UNKNOWN
